jogger_python/__init__.py
jogger_python/config.py
jogger_python/test/__init__.py
jogger_python/test/config.py
jogger_python/test/logger.py
jogger_python-1.8.0.dist-info/LICENSE
jogger_python-1.8.0.dist-info/METADATA
jogger_python-1.8.0.dist-info/WHEEL
jogger_python-1.8.0.dist-info/top_level.txt
jogger_python-1.8.0.dist-info/RECORD
